{
    "__comment": "Made with TheDestruc7i0n's advancements generator: https://advancements.thedestruc7i0n.ca",
    "display": {
        "title": {
            "text": "Warm summer"
        },
        "description": {
            "text": "obtain a magma block"
        },
        "icon": {
            "item": "minecraft:magma_block"
        },
        "frame": "task",
        "show_toast": true,
        "announce_to_chat": true,
        "hidden": false
    },
    "criteria": {
        "cobble": {
            "trigger": "minecraft:inventory_changed",
            "conditions": {
                "items": [
					{
						"items": [
							"minecraft:magma_block"
						]
					}
                ]
            }
        }
    },
    "parent": "obs:ob/coal"
}